emr_password_manager/__init__.py
emr_password_manager/emr_password_manager.py
emr_password_manager-1.2.0.dist-info/METADATA
emr_password_manager-1.2.0.dist-info/WHEEL
emr_password_manager-1.2.0.dist-info/top_level.txt
emr_password_manager-1.2.0.dist-info/RECORD
