Metadata-Version: 2.1
Name: emr-password-manager
Version: 1.2.0
Summary: A simple password manager for generating and validating passwords.
Home-page: https://github.com/EmrD/python-password-manager-library
Author: Emr
Author-email: 
Classifier: Programming Language :: Python :: 3
Classifier: Operating System :: OS Independent
Requires-Python: >=3.6
